tests/__init__.py
tests/test_database_client.py
tests/test_hashing_client.py
tests/test_load_secrets.py
tests/test_logger.py
tommytomato_utils/__init__.py
tommytomato_utils/database_client/__init__.py
tommytomato_utils/database_client/database_client.py
tommytomato_utils/database_client/exceptions.py
tommytomato_utils/hashing_client/__init__.py
tommytomato_utils/hashing_client/constants.py
tommytomato_utils/hashing_client/exceptions.py
tommytomato_utils/hashing_client/hashing_client.py
tommytomato_utils/load_secrets/__init__.py
tommytomato_utils/load_secrets/environment.py
tommytomato_utils/load_secrets/exceptions.py
tommytomato_utils/load_secrets/secrets_loader.py
tommytomato_utils/logger/__init__.py
tommytomato_utils/logger/configure_logging.py
tommytomato_utils/logger/db_logging_handler.py
tommytomato_utils/logger/log_status.py
tommytomato_utils/logger/logger.py
tommytomato_operation_utils-2.0.0.dist-info/METADATA
tommytomato_operation_utils-2.0.0.dist-info/WHEEL
tommytomato_operation_utils-2.0.0.dist-info/top_level.txt
tommytomato_operation_utils-2.0.0.dist-info/RECORD
