Metadata-Version: 2.1
Name: tommytomato_operation_utils
Version: 2.0.0
Summary: Utility package for hash generation and database operations.
Home-page: https://github.com/felix_bithero/tommytomato_operation_utils
Author: felix_bithero
Author-email: felixl@bithero.com
Classifier: Programming Language :: Python :: 3
Classifier: License :: OSI Approved :: MIT License
Classifier: Operating System :: OS Independent
Requires-Python: >=3.11
Requires-Dist: boto3==1.34.130
Requires-Dist: pandas==2.2.2
Requires-Dist: sqlalchemy==2.0.31
Requires-Dist: tenacity==8.5.0
Requires-Dist: python-dotenv==0.18.0
Requires-Dist: psycopg2-binary==2.9.9
Requires-Dist: typeguard==4.3.0
Provides-Extra: linting
Requires-Dist: flake8==7.1.0; extra == "linting"
Requires-Dist: isort==5.10.1; extra == "linting"
Requires-Dist: pre-commit; extra == "linting"
Requires-Dist: importlib_metadata==4.8.3; extra == "linting"
Provides-Extra: testing
Requires-Dist: pytest; extra == "testing"
Requires-Dist: pytest-cov; extra == "testing"
Requires-Dist: freezegun; extra == "testing"
